{
  "version": "6",
  "dialect": "sqlite",
  "id": "11ac0716-3b44-4963-8790-5a3fb03c9fdf",
  "prevId": "00000000-0000-0000-0000-000000000000",
  "tables": {
    "pools": {
      "name": "pools",
      "columns": {
        "id": {
          "name": "id",
          "type": "integer",
          "primaryKey": true,
          "notNull": true,
          "autoincrement": true
        },
        "token_a_id": {
          "name": "token_a_id",
          "type": "integer",
          "primaryKey": false,
          "notNull": true,
          "autoincrement": false
        },
        "token_b_id": {
          "name": "token_b_id",
          "type": "integer",
          "primaryKey": false,
          "notNull": true,
          "autoincrement": false
        },
        "reserve_a": {
          "name": "reserve_a",
          "type": "text",
          "primaryKey": false,
          "notNull": true,
          "autoincrement": false
        },
        "reserve_b": {
          "name": "reserve_b",
          "type": "text",
          "primaryKey": false,
          "notNull": true,
          "autoincrement": false
        },
        "fee_tier": {
          "name": "fee_tier",
          "type": "integer",
          "primaryKey": false,
          "notNull": true,
          "autoincrement": false
        },
        "total_supply": {
          "name": "total_supply",
          "type": "text",
          "primaryKey": false,
          "notNull": true,
          "autoincrement": false
        },
        "tvl": {
          "name": "tvl",
          "type": "real",
          "primaryKey": false,
          "notNull": true,
          "autoincrement": false
        },
        "volume_24h": {
          "name": "volume_24h",
          "type": "real",
          "primaryKey": false,
          "notNull": true,
          "autoincrement": false
        },
        "apy": {
          "name": "apy",
          "type": "real",
          "primaryKey": false,
          "notNull": true,
          "autoincrement": false
        },
        "created_at": {
          "name": "created_at",
          "type": "text",
          "primaryKey": false,
          "notNull": true,
          "autoincrement": false
        },
        "updated_at": {
          "name": "updated_at",
          "type": "text",
          "primaryKey": false,
          "notNull": true,
          "autoincrement": false
        }
      },
      "indexes": {},
      "foreignKeys": {
        "pools_token_a_id_tokens_id_fk": {
          "name": "pools_token_a_id_tokens_id_fk",
          "tableFrom": "pools",
          "tableTo": "tokens",
          "columnsFrom": [
            "token_a_id"
          ],
          "columnsTo": [
            "id"
          ],
          "onDelete": "no action",
          "onUpdate": "no action"
        },
        "pools_token_b_id_tokens_id_fk": {
          "name": "pools_token_b_id_tokens_id_fk",
          "tableFrom": "pools",
          "tableTo": "tokens",
          "columnsFrom": [
            "token_b_id"
          ],
          "columnsTo": [
            "id"
          ],
          "onDelete": "no action",
          "onUpdate": "no action"
        }
      },
      "compositePrimaryKeys": {},
      "uniqueConstraints": {},
      "checkConstraints": {}
    },
    "positions": {
      "name": "positions",
      "columns": {
        "id": {
          "name": "id",
          "type": "integer",
          "primaryKey": true,
          "notNull": true,
          "autoincrement": true
        },
        "pool_id": {
          "name": "pool_id",
          "type": "integer",
          "primaryKey": false,
          "notNull": true,
          "autoincrement": false
        },
        "owner_address": {
          "name": "owner_address",
          "type": "text",
          "primaryKey": false,
          "notNull": true,
          "autoincrement": false
        },
        "liquidity": {
          "name": "liquidity",
          "type": "text",
          "primaryKey": false,
          "notNull": true,
          "autoincrement": false
        },
        "accumulated_fees_a": {
          "name": "accumulated_fees_a",
          "type": "text",
          "primaryKey": false,
          "notNull": true,
          "autoincrement": false
        },
        "accumulated_fees_b": {
          "name": "accumulated_fees_b",
          "type": "text",
          "primaryKey": false,
          "notNull": true,
          "autoincrement": false
        },
        "share_percentage": {
          "name": "share_percentage",
          "type": "real",
          "primaryKey": false,
          "notNull": true,
          "autoincrement": false
        },
        "value_usd": {
          "name": "value_usd",
          "type": "real",
          "primaryKey": false,
          "notNull": true,
          "autoincrement": false
        },
        "created_at": {
          "name": "created_at",
          "type": "text",
          "primaryKey": false,
          "notNull": true,
          "autoincrement": false
        },
        "last_fee_claim": {
          "name": "last_fee_claim",
          "type": "text",
          "primaryKey": false,
          "notNull": true,
          "autoincrement": false
        }
      },
      "indexes": {},
      "foreignKeys": {
        "positions_pool_id_pools_id_fk": {
          "name": "positions_pool_id_pools_id_fk",
          "tableFrom": "positions",
          "tableTo": "pools",
          "columnsFrom": [
            "pool_id"
          ],
          "columnsTo": [
            "id"
          ],
          "onDelete": "no action",
          "onUpdate": "no action"
        }
      },
      "compositePrimaryKeys": {},
      "uniqueConstraints": {},
      "checkConstraints": {}
    },
    "swaps": {
      "name": "swaps",
      "columns": {
        "id": {
          "name": "id",
          "type": "integer",
          "primaryKey": true,
          "notNull": true,
          "autoincrement": true
        },
        "pool_id": {
          "name": "pool_id",
          "type": "integer",
          "primaryKey": false,
          "notNull": true,
          "autoincrement": false
        },
        "user_address": {
          "name": "user_address",
          "type": "text",
          "primaryKey": false,
          "notNull": true,
          "autoincrement": false
        },
        "token_in_id": {
          "name": "token_in_id",
          "type": "integer",
          "primaryKey": false,
          "notNull": true,
          "autoincrement": false
        },
        "token_out_id": {
          "name": "token_out_id",
          "type": "integer",
          "primaryKey": false,
          "notNull": true,
          "autoincrement": false
        },
        "amount_in": {
          "name": "amount_in",
          "type": "text",
          "primaryKey": false,
          "notNull": true,
          "autoincrement": false
        },
        "amount_out": {
          "name": "amount_out",
          "type": "text",
          "primaryKey": false,
          "notNull": true,
          "autoincrement": false
        },
        "fee": {
          "name": "fee",
          "type": "text",
          "primaryKey": false,
          "notNull": true,
          "autoincrement": false
        },
        "price_impact": {
          "name": "price_impact",
          "type": "real",
          "primaryKey": false,
          "notNull": true,
          "autoincrement": false
        },
        "tx_digest": {
          "name": "tx_digest",
          "type": "text",
          "primaryKey": false,
          "notNull": true,
          "autoincrement": false
        },
        "created_at": {
          "name": "created_at",
          "type": "text",
          "primaryKey": false,
          "notNull": true,
          "autoincrement": false
        }
      },
      "indexes": {
        "swaps_tx_digest_unique": {
          "name": "swaps_tx_digest_unique",
          "columns": [
            "tx_digest"
          ],
          "isUnique": true
        }
      },
      "foreignKeys": {
        "swaps_pool_id_pools_id_fk": {
          "name": "swaps_pool_id_pools_id_fk",
          "tableFrom": "swaps",
          "tableTo": "pools",
          "columnsFrom": [
            "pool_id"
          ],
          "columnsTo": [
            "id"
          ],
          "onDelete": "no action",
          "onUpdate": "no action"
        },
        "swaps_token_in_id_tokens_id_fk": {
          "name": "swaps_token_in_id_tokens_id_fk",
          "tableFrom": "swaps",
          "tableTo": "tokens",
          "columnsFrom": [
            "token_in_id"
          ],
          "columnsTo": [
            "id"
          ],
          "onDelete": "no action",
          "onUpdate": "no action"
        },
        "swaps_token_out_id_tokens_id_fk": {
          "name": "swaps_token_out_id_tokens_id_fk",
          "tableFrom": "swaps",
          "tableTo": "tokens",
          "columnsFrom": [
            "token_out_id"
          ],
          "columnsTo": [
            "id"
          ],
          "onDelete": "no action",
          "onUpdate": "no action"
        }
      },
      "compositePrimaryKeys": {},
      "uniqueConstraints": {},
      "checkConstraints": {}
    },
    "tokens": {
      "name": "tokens",
      "columns": {
        "id": {
          "name": "id",
          "type": "integer",
          "primaryKey": true,
          "notNull": true,
          "autoincrement": true
        },
        "symbol": {
          "name": "symbol",
          "type": "text",
          "primaryKey": false,
          "notNull": true,
          "autoincrement": false
        },
        "name": {
          "name": "name",
          "type": "text",
          "primaryKey": false,
          "notNull": true,
          "autoincrement": false
        },
        "decimals": {
          "name": "decimals",
          "type": "integer",
          "primaryKey": false,
          "notNull": true,
          "autoincrement": false
        },
        "address": {
          "name": "address",
          "type": "text",
          "primaryKey": false,
          "notNull": true,
          "autoincrement": false
        },
        "logo_url": {
          "name": "logo_url",
          "type": "text",
          "primaryKey": false,
          "notNull": false,
          "autoincrement": false
        },
        "created_at": {
          "name": "created_at",
          "type": "text",
          "primaryKey": false,
          "notNull": true,
          "autoincrement": false
        }
      },
      "indexes": {
        "tokens_symbol_unique": {
          "name": "tokens_symbol_unique",
          "columns": [
            "symbol"
          ],
          "isUnique": true
        }
      },
      "foreignKeys": {},
      "compositePrimaryKeys": {},
      "uniqueConstraints": {},
      "checkConstraints": {}
    }
  },
  "views": {},
  "enums": {},
  "_meta": {
    "schemas": {},
    "tables": {},
    "columns": {}
  },
  "internal": {
    "indexes": {}
  }
}